LICENSE.md
MANIFEST.in
README.rst
setup.py
ovp_news/.gitignore
ovp_news/__init__.py
ovp_news/apps.py
ovp_news/emails.py
ovp_news/helpers.py
ovp_news.egg-info/PKG-INFO
ovp_news.egg-info/SOURCES.txt
ovp_news.egg-info/dependency_links.txt
ovp_news.egg-info/not-zip-safe
ovp_news.egg-info/requires.txt
ovp_news.egg-info/top_level.txt
ovp_news/__pycache__/__init__.cpython-35.pyc
ovp_news/migrations/__init__.py
ovp_news/models/__init__.py
ovp_news/models/__pycache__/__init__.cpython-35.pyc
ovp_news/models/__pycache__/password_recovery.cpython-35.pyc
ovp_news/models/__pycache__/profile.cpython-35.pyc
ovp_news/models/__pycache__/user.cpython-35.pyc
ovp_news/templates/__init__.py
ovp_news/templates/__pycache__/__init__.cpython-35.pyc
ovp_news/templates/email/__init__.py
ovp_news/templates/email/__pycache__/__init__.cpython-35.pyc
ovp_news/tests/__init__.py
ovp_news/tests/runtests.py
ovp_news/tests/__pycache__/__init__.cpython-35.pyc
ovp_news/tests/__pycache__/helpers.cpython-35.pyc
ovp_news/tests/__pycache__/test_emails.cpython-35.pyc
ovp_news/tests/__pycache__/test_execution.cpython-35.pyc
ovp_news/tests/__pycache__/test_filters.cpython-35.pyc
ovp_news/tests/__pycache__/test_models.cpython-35.pyc