Metadata-Version: 1.1
Name: ovp-news
Version: 0.1.0
Summary: This module contains  functionality for sending newsletter and digests to users and leads
Home-page: https://github.com/OpenVolunteeringPlatform/ovp-news
Author: Atados
Author-email: arroyo@atados.com.br
License: AGPL
Download-URL: https://github.com/OpenVolunteeringPlatform/ovp-news/tarball/0.1.0
Platform: UNKNOWN
